semantic_embeddings-0.1.1.dist-info/licenses/LICENSE
sembeddings/__init__.py
sembeddings/grace.py
sembeddings/rade.py
sembeddings/utils.py
sembeddings/measures/__init__.py
sembeddings/measures/correlation.py
sembeddings/measures/qpp.py
semantic_embeddings-0.1.1.dist-info/METADATA
semantic_embeddings-0.1.1.dist-info/WHEEL
semantic_embeddings-0.1.1.dist-info/top_level.txt
semantic_embeddings-0.1.1.dist-info/RECORD
